pyaccsharedmemory.py
pyaccsharedmemory-0.0.2.dist-info/LICENSE
pyaccsharedmemory-0.0.2.dist-info/METADATA
pyaccsharedmemory-0.0.2.dist-info/WHEEL
pyaccsharedmemory-0.0.2.dist-info/top_level.txt
pyaccsharedmemory-0.0.2.dist-info/RECORD
