Metadata-Version: 2.1
Name: pyaccsharedmemory
Version: 0.0.2
Summary: ACC shared memory reader in python
Home-page: https://github.com/rrennoir/PyAccSharedMemory
Author: Ryan Rennoir
Author-email: ryanrennoir9@gmail.com
Classifier: Operating System :: Microsoft
Classifier: Programming Language :: Python :: 3
Classifier: Programming Language :: Python :: 3.8
Classifier: Programming Language :: Python :: 3.9
Classifier: Programming Language :: Python :: 3.10
Classifier: License :: OSI Approved :: MIT License
License-File: LICENSE
